.gitignore
LICENSE
Makefile
README.md
requirements.txt
setup.py
.github/workflows/publish.yml
.github/workflows/tests.yml
actionpack/__init__.py
actionpack/action.py
actionpack/procedure.py
actionpack/utils.py
actionpack.egg-info/PKG-INFO
actionpack.egg-info/SOURCES.txt
actionpack.egg-info/dependency_links.txt
actionpack.egg-info/requires.txt
actionpack.egg-info/top_level.txt
actionpack/actions/__init__.py
actionpack/actions/call.py
actionpack/actions/make_request.py
actionpack/actions/pipeline.py
actionpack/actions/read.py
actionpack/actions/read_input.py
actionpack/actions/retry_policy.py
actionpack/actions/serialization.py
actionpack/actions/write.py
tests/__init__.py
tests/actionpack/__init__.py
tests/actionpack/test_action.py
tests/actionpack/test_procedure.py
tests/actionpack/test_utils.py
tests/actionpack/actions/__init__.py
tests/actionpack/actions/test_call.py
tests/actionpack/actions/test_make_request.py
tests/actionpack/actions/test_pipeline.py
tests/actionpack/actions/test_read.py
tests/actionpack/actions/test_read_input.py
tests/actionpack/actions/test_retry_policy.py
tests/actionpack/actions/test_serialization.py
tests/actionpack/actions/test_write.py