Metadata-Version: 2.1
Name: actionpack
Version: 1.5.0
Summary: a lib for describing Actions and how they should be performed
Home-page: https://github.com/withtwoemms/actionpack
Author: Emmanuel I. Obi
Maintainer: Emmanuel I. Obi
Maintainer-email: withtwoemms@gmail.com
License: UNKNOWN
Platform: UNKNOWN
Classifier: Development Status :: 3 - Alpha
Classifier: Intended Audience :: Developers
Classifier: Intended Audience :: Education
Classifier: Intended Audience :: Science/Research
Classifier: Topic :: Software Development :: Build Tools
Classifier: License :: OSI Approved :: MIT License
Classifier: Programming Language :: Python :: 3.6
Classifier: Programming Language :: Python :: 3.7
Classifier: Programming Language :: Python :: 3.8
Classifier: Programming Language :: Python :: 3.9
License-File: LICENSE
